xenoverse/__init__.py
xenoverse/anyhvac/__init__.py
xenoverse/anyhvac/anyhvac_env.py
xenoverse/anyhvac/anyhvac_env_vis.py
xenoverse/anyhvac/anyhvac_sampler.py
xenoverse/anyhvac/anyhvac_solver.py
xenoverse/anyhvac/anyhvac_utils.py
xenoverse/anyhvac/test.py
xenoverse/anyhvac/test_file.py
xenoverse/anyhvacv2/__init__.py
xenoverse/anyhvacv2/anyhvac_env.py
xenoverse/anyhvacv2/anyhvac_env_vis.py
xenoverse/anyhvacv2/anyhvac_sampler.py
xenoverse/anyhvacv2/anyhvac_solver.py
xenoverse/anyhvacv2/anyhvac_utils.py
xenoverse/anyhvacv2/test.py
xenoverse/anyhvacv2/test_file.py
xenoverse/anymdp/__init__.py
xenoverse/anymdp/anymdp_env.py
xenoverse/anymdp/anymdp_solver_mbrl.py
xenoverse/anymdp/anymdp_solver_opt.py
xenoverse/anymdp/anymdp_solver_q.py
xenoverse/anymdp/solver.py
xenoverse/anymdp/task_sampler.py
xenoverse/anymdp/task_sampler_utils.py
xenoverse/anymdp/test.py
xenoverse/anymdp/test2.py
xenoverse/anymdp/test_3.py
xenoverse/anymdp/test_ppo.py
xenoverse/anymdp/test_utils.py
xenoverse/anymdp/visualizer.py
xenoverse/anymdpv2/__init__.py
xenoverse/anymdpv2/anymdp_env.py
xenoverse/anymdpv2/task_sampler.py
xenoverse/anymdpv2/test.py
xenoverse/anymdpv2/test_ppo.py
xenoverse/anymdpv2/visualizer.py
xenoverse/linds/__init__.py
xenoverse/linds/inspect_pkl.py
xenoverse/linds/linds_env.py
xenoverse/linds/solver.py
xenoverse/linds/task_sampler.py
xenoverse/linds/test.py
xenoverse/linds/test_ppo.py
xenoverse/linds/visualizer.py
xenoverse/mazeworld/__init__.py
xenoverse/mazeworld/agents/__init__.py
xenoverse/mazeworld/agents/agent_base.py
xenoverse/mazeworld/agents/oracle_agent.py
xenoverse/mazeworld/agents/smart_slam_agent.py
xenoverse/mazeworld/demo/__init__.py
xenoverse/mazeworld/demo/agent_play_demo.py
xenoverse/mazeworld/demo/keyboard_play_demo.py
xenoverse/mazeworld/envs/__init__.py
xenoverse/mazeworld/envs/dynamics.py
xenoverse/mazeworld/envs/maze_base.py
xenoverse/mazeworld/envs/maze_continuous_3d.py
xenoverse/mazeworld/envs/maze_env.py
xenoverse/mazeworld/envs/ray_caster_utils.py
xenoverse-0.1.10.0.dist-info/licenses/LICENSE
xenoverse-0.1.10.0.dist-info/METADATA
xenoverse-0.1.10.0.dist-info/WHEEL
xenoverse-0.1.10.0.dist-info/top_level.txt
xenoverse-0.1.10.0.dist-info/RECORD
