Metadata-Version: 2.4
Name: xenoverse
Version: 0.1.10.0
Summary: Collection of xeno-world environments for meta-training of general-purpose learning agents (GLAs)
Home-page: https://github.com/FutureAGI/xenoverse
Author: WorldEditors
Author-email: 
License: Apache
Requires-Python: >=3.8
License-File: LICENSE
Requires-Dist: gymnasium>=1.0.0
Requires-Dist: numpy>=1.24.4
Requires-Dist: Pillow>=6.2.2
Requires-Dist: six>=1.12.0
Requires-Dist: pygame>=2.6.0
Requires-Dist: numba>=0.58.1
Requires-Dist: scipy
Dynamic: author
Dynamic: description
Dynamic: description-content-type
Dynamic: home-page
Dynamic: license
Dynamic: license-file
Dynamic: requires-dist
Dynamic: requires-python
Dynamic: summary
